clypi/__init__.py
clypi/_colors.py
clypi/_configuration.py
clypi/_exceptions.py
clypi/_prompts.py
clypi/_type_util.py
clypi/_util.py
clypi/parsers.py
clypi/py.typed
clypi/_cli/__init__.py
clypi/_cli/arg_config.py
clypi/_cli/arg_parser.py
clypi/_cli/autocomplete.py
clypi/_cli/context.py
clypi/_cli/deferred.py
clypi/_cli/distance.py
clypi/_cli/formatter.py
clypi/_cli/main.py
clypi/_components/align.py
clypi/_components/boxed.py
clypi/_components/indented.py
clypi/_components/separator.py
clypi/_components/spinners.py
clypi/_components/stack.py
clypi/_components/wraps.py
clypi/_data/boxes.py
clypi/_data/dunders.py
clypi/_data/spinners.py
clypi-1.8.2.dist-info/METADATA
clypi-1.8.2.dist-info/WHEEL
clypi-1.8.2.dist-info/licenses/LICENSE
clypi-1.8.2.dist-info/RECORD
