Metadata-Version: 2.4
Name: clypi
Version: 1.8.2
Summary: Your all-in-one for beautiful, lightweight, prod-ready CLIs
Project-URL: Documentation, https://danimelchor.github.io/clypi/
Project-URL: Homepage, https://danimelchor.github.io/clypi/
Project-URL: Repository, https://github.com/danimelchor/clypi
Project-URL: Issues, https://github.com/danimelchor/clypi/issues
Author-email: Daniel Melchor <dmelchor@pm.me>
License-Expression: MIT
License-File: LICENSE
Keywords: cli,terminal,ui
Requires-Python: >=3.11
Requires-Dist: python-dateutil>=2.9.0.post0
Requires-Dist: typing-extensions>=4.4.0
Provides-Extra: dev
Requires-Dist: anyio>=4.8.0; extra == 'dev'
Requires-Dist: codespell>=2.4.1; extra == 'dev'
Requires-Dist: pyright[nodejs]>=1.1.396; extra == 'dev'
Requires-Dist: pytest>=8.3.5; extra == 'dev'
Requires-Dist: ruff>=0.9.7; extra == 'dev'
Requires-Dist: types-python-dateutil>=2.9.0.20241206; extra == 'dev'
Provides-Extra: docs
Requires-Dist: markdown-callouts>=0.4.0; extra == 'docs'
Requires-Dist: mkdocs-glightbox>=0.4.0; extra == 'docs'
Requires-Dist: mkdocs-material>=9.6.8; extra == 'docs'
Requires-Dist: pygments>=2.19.1; extra == 'docs'
Requires-Dist: termynal>=0.13.0; extra == 'docs'
